base_template/__init__.py
base_template/apps.py
base_template/context_processors.py
base_template/settings.py
base_template/utils.py
base_template/__pycache__/__init__.cpython-38.pyc
base_template/__pycache__/apps.cpython-38.pyc
base_template/__pycache__/context_processors.cpython-38.pyc
base_template/__pycache__/settings.cpython-38.pyc
base_template/__pycache__/utils.cpython-38.pyc
base_template/static/base_template/css/style.bundle.css
base_template/static/base_template/css/style.bundle.rtl.css
base_template/static/base_template/images/icon.ico
base_template/static/base_template/images/icon.svg
base_template/static/base_template/images/logo-dark.svg
base_template/static/base_template/images/logo-white.svg
base_template/static/base_template/images/logo.png
base_template/static/base_template/images/smartphone-2-dark.svg
base_template/static/base_template/images/smartphone-2.svg
base_template/static/base_template/images/user.jpg
base_template/static/base_template/js/scripts.bundle.js
base_template/static/base_template/js/utils.js
base_template/static/base_template/plugins/global/plugins.bundle.css
base_template/static/base_template/plugins/global/plugins.bundle.js
base_template/static/base_template/plugins/global/plugins.bundle.rtl.css
base_template/static/base_template/plugins/global/fonts/@fortawesome/fa-brands-400.ttf
base_template/static/base_template/plugins/global/fonts/@fortawesome/fa-brands-400.woff2
base_template/static/base_template/plugins/global/fonts/@fortawesome/fa-regular-400.ttf
base_template/static/base_template/plugins/global/fonts/@fortawesome/fa-regular-400.woff2
base_template/static/base_template/plugins/global/fonts/@fortawesome/fa-solid-900.ttf
base_template/static/base_template/plugins/global/fonts/@fortawesome/fa-solid-900.woff2
base_template/static/base_template/plugins/global/fonts/@fortawesome/fa-v4compatibility.ttf
base_template/static/base_template/plugins/global/fonts/@fortawesome/fa-v4compatibility.woff2
django_base_template-1.0.8.dist-info/LICENSE
django_base_template-1.0.8.dist-info/METADATA
django_base_template-1.0.8.dist-info/WHEEL
django_base_template-1.0.8.dist-info/top_level.txt
django_base_template-1.0.8.dist-info/RECORD
